sphinxcontrib/test_reports/__init__.py
sphinxcontrib/test_reports/config.py
sphinxcontrib/test_reports/environment.py
sphinxcontrib/test_reports/exceptions.py
sphinxcontrib/test_reports/jsonparser.py
sphinxcontrib/test_reports/junitparser.py
sphinxcontrib/test_reports/test_reports.py
sphinxcontrib/test_reports/css/common.css
sphinxcontrib/test_reports/directives/__init__.py
sphinxcontrib/test_reports/directives/test_case.py
sphinxcontrib/test_reports/directives/test_common.py
sphinxcontrib/test_reports/directives/test_env.py
sphinxcontrib/test_reports/directives/test_file.py
sphinxcontrib/test_reports/directives/test_report.py
sphinxcontrib/test_reports/directives/test_report_template.txt
sphinxcontrib/test_reports/directives/test_results.py
sphinxcontrib/test_reports/directives/test_suite.py
sphinxcontrib/test_reports/functions/__init__.py
sphinxcontrib/test_reports/schemas/JUnit.xsd
sphinx_test_reports-1.3.2.dist-info/licenses/LICENSE
sphinx_test_reports-1.3.2.dist-info/WHEEL
sphinx_test_reports-1.3.2.dist-info/METADATA
sphinx_test_reports-1.3.2.dist-info/RECORD
